pyjdx/__init__.py
pyjdx/jdx.py
pyjdx-0.0.1.dist-info/metadata.json
pyjdx-0.0.1.dist-info/top_level.txt
pyjdx-0.0.1.dist-info/RECORD
pyjdx-0.0.1.dist-info/METADATA
pyjdx-0.0.1.dist-info/WHEEL
pyjdx-0.0.1.dist-info/DESCRIPTION.rst
