Metadata-Version: 2.0
Name: pyjdx
Version: 0.0.1
Summary: A reader of JCAMP-DX spectral data files
Home-page: https://github.com/vulpicastor/pyjdx
Author: Lizhou Sha
Author-email: slz@mit.edu
License: MIT
Keywords: spectroscopy chemistry astronomy atmospheric planetary science
Platform: UNKNOWN
Classifier: Development Status :: 3 - Alpha
Classifier: Intended Audience :: Science/Research
Classifier: License :: OSI Approved :: MIT License
Classifier: Operating System :: OS Independent
Classifier: Programming Language :: Python :: 2
Classifier: Programming Language :: Python :: 2.7
Classifier: Programming Language :: Python :: 3
Classifier: Programming Language :: Python :: 3.4
Classifier: Topic :: Scientific/Engineering :: Astronomy
Classifier: Topic :: Scientific/Engineering :: Atmospheric Science
Classifier: Topic :: Scientific/Engineering :: Chemistry
Classifier: Topic :: Software Development :: Libraries :: Python Modules
Requires-Dist: numpy
